LICENSE
pyproject.toml
.github/README.md
arxiv_explorer/__init__.py
arxiv_explorer/entrypoint.py
arxiv_explorer/providers.py
arxiv_explorer/tui/__init__.py
arxiv_explorer/tui/search.py
arxiv_explorer/tui/splash.py
arxiv_explorer-0.0.1.dist-info/METADATA
arxiv_explorer-0.0.1.dist-info/WHEEL
arxiv_explorer-0.0.1.dist-info/entry_points.txt
arxiv_explorer-0.0.1.dist-info/licenses/LICENSE
arxiv_explorer-0.0.1.dist-info/RECORD
